twsqlparser/__init__.py
twsqlparser/__pkg_info__.py
twsqlparser/enums.py
twsqlparser/internal_exceptions.py
twsqlparser/twsp.py
twsqlparser-1.0.4.dist-info/LICENSE
twsqlparser-1.0.4.dist-info/METADATA
twsqlparser-1.0.4.dist-info/WHEEL
twsqlparser-1.0.4.dist-info/top_level.txt
twsqlparser-1.0.4.dist-info/RECORD
