Metadata-Version: 2.1
Name: twsqlparser
Version: 1.0.4
Summary: 2way SQL parser for Python
Home-page: https://github.com/gomachssm/twsqlparser
Author: gomachssm
License: Apache License, Version 2.0
Keywords: two way sql twsql twowaysql two-way 2way 2way-sql
Platform: UNKNOWN
Classifier: License :: OSI Approved :: Apache Software License
Classifier: Programming Language :: Python :: 3.6
Classifier: Programming Language :: Python :: 3.7
Classifier: Programming Language :: Python :: 3.8
Classifier: Programming Language :: Python :: 3.9
Requires-Python: >=3.6
License-File: LICENSE
